lazytime/__init__.py
lazytime/lazytime.py
lazytime-0.0.1.dist-info/METADATA
lazytime-0.0.1.dist-info/WHEEL
lazytime-0.0.1.dist-info/top_level.txt
lazytime-0.0.1.dist-info/RECORD
