Metadata-Version: 2.1
Name: lazytime
Version: 0.0.1
Summary: 基于python3的时间模块的懒人封包
Home-page: https://gitee.com/ZeroSeeker/lazytime
Author: ZeroSeeker
Author-email: zeroseeker@foxmail.com
License: UNKNOWN
Platform: UNKNOWN
Classifier: Programming Language :: Python :: 3
Classifier: License :: OSI Approved :: MIT License
Classifier: Operating System :: OS Independent
Requires-Dist: pytz (==2021.3)
